netbox_celery/__init__.py
netbox_celery/api/__init__.py
netbox_celery/api/serializers.py
netbox_celery/api/urls.py
netbox_celery/api/views.py
netbox_celery/celery.py
netbox_celery/choices.py
netbox_celery/filtersets.py
netbox_celery/forms.py
netbox_celery/migrations/0001_initial.py
netbox_celery/migrations/0002_rename_data_celeryresult_kwargs_celeryresult_args.py
netbox_celery/migrations/0003_celeryresult_result.py
netbox_celery/migrations/0004_alter_celeryresult_custom_field_data.py
netbox_celery/migrations/__init__.py
netbox_celery/models.py
netbox_celery/navigation.py
netbox_celery/schedule.py
netbox_celery/settings_funcs.py
netbox_celery/tables.py
netbox_celery/tasks.py
netbox_celery/templates/netbox_celery/celery_task_form.html
netbox_celery/templates/netbox_celery/celeryresult.html
netbox_celery/tests/__init__.py
netbox_celery/tests/test_api.py
netbox_celery/tests/test_views.py
netbox_celery/urls.py
netbox_celery/views.py
netbox_celery-0.1.1b7.dist-info/LICENSE
netbox_celery-0.1.1b7.dist-info/METADATA
netbox_celery-0.1.1b7.dist-info/WHEEL
netbox_celery-0.1.1b7.dist-info/RECORD
