Metadata-Version: 2.1
Name: netbox-celery
Version: 0.1.1b7
Summary: 
Author: OpticoreIT
Author-email: opensource@opticoreit.com
Requires-Python: >=3.8,<4.0
Classifier: Programming Language :: Python :: 3
Classifier: Programming Language :: Python :: 3.8
Classifier: Programming Language :: Python :: 3.9
Classifier: Programming Language :: Python :: 3.10
Classifier: Programming Language :: Python :: 3.11
Requires-Dist: celery (>=5.2.7,<6.0.0)
Requires-Dist: django-celery-beat (>=2.3.0,<3.0.0)
